hulihutu/__init__.py
hulihutu/generate_game.py
hulihutu/mdp.py
hulihutu/network.py
hulihutu/testBoard.py
hulihutu/test_tictac.py
hulihutu/tictac.py
hulihutu-1.0.5.dist-info/DESCRIPTION.rst
hulihutu-1.0.5.dist-info/METADATA
hulihutu-1.0.5.dist-info/RECORD
hulihutu-1.0.5.dist-info/WHEEL
hulihutu-1.0.5.dist-info/metadata.json
hulihutu-1.0.5.dist-info/top_level.txt
