Metadata-Version: 2.0
Name: hulihutu
Version: 1.0.5
Summary: An tictactoe AI with reinforcement learning
Home-page: https://github.com/sepmein/tictac
Author: Spencer Zhang
Author-email: sepmein@hotmail.com
License: MIT
Keywords: reinforcement learning machine learning tictactoe game
Platform: UNKNOWN
Classifier: Development Status :: 3 - Alpha
Classifier: Intended Audience :: Developers
Classifier: Topic :: Scientific/Engineering :: Artificial Intelligence
Classifier: License :: OSI Approved :: MIT License
Classifier: Programming Language :: Python :: 2
Classifier: Programming Language :: Python :: 2.7
Classifier: Programming Language :: Python :: 3
Classifier: Programming Language :: Python :: 3.3
Classifier: Programming Language :: Python :: 3.4
Classifier: Programming Language :: Python :: 3.5
Requires-Dist: numpy
Requires-Dist: pymongo
